{"cameraMode":{"drawMode":0,"name":"Shaded","section":"Shading Mode"},"sceneLighting":true,"audioPlay":false,"sceneViewState":{"m_AlwaysRefresh":false,"showFog":true,"showSkybox":true,"showFlares":true,"showImageEffects":true,"showParticleSystems":true,"showVisualEffectGraphs":true,"m_FxEnabled":true},"in2DMode":false,"pivot":{"x":-22.96013832092285,"y":-11.454649925231934,"z":29.95197105407715},"rotation":{"x":-0.1763187199831009,"y":0.4844665825366974,"z":-0.10038764774799347,"w":-0.8509833216667175},"size":22.761981964111329,"orthographic":false}